Workbook

Sheet Assets
A1: Asset | B1: Sector | C1: Expected_Return | D1: Weight
A2: US_Tech_Equity | B2: Equity | C2: 0.14 | D2: 0.026238
A3: US_Healthcare_Equity | B3: Equity | C3: 0.1 | D3: 0.075198
A4: US_Financials_Equity | B4: Equity | C4: 0.09 | D4: 0
A5: US_Energy_Equity | B5: Equity | C5: 0.08 | D5: 0
A6: US_Consumer_Equity | B6: Equity | C6: 0.095 | D6: 0.151981
A7: European_Equity | B7: Equity | C7: 0.075 | D7: 0
A8: Emerging_Markets_Equity | B8: Equity | C8: 0.11 | D8: 0.046583
A9: US_Govt_Bonds | B9: Fixed Income | C9: 0.035 | D9: 0.25
A10: US_Corporate_Bonds | B10: Fixed Income | C10: 0.045 | D10: 0.248927
A11: Global_Bonds | B11: Fixed Income | C11: 0.03 | D11: 0
A12: REIT | B12: Alternatives | C12: 0.08 | D12: 0
A13: Gold | B13: Alternatives | C13: 0.05 | D13: 0.083975
... A15: Money_Market | B15: Cash | C15: 0.02 | D15: 0.117098
A17: Sum of Weights (must = 100%) | D17: =SUM(D2:D15)
A18: Portfolio Expected Return | D18: =SUMPRODUCT(C2:C15,D2:D15)
A19: Portfolio Volatility (see Covariance sheet) | D19: =Covariance!B1
A20: Sharpe Ratio (risk-free = 2%) | D20: =(D18-0.02)/D19
A22: Sector Totals
A23: Equity | D23: =SUMIF(B2:B15,A23,D2:D15)
A24: Fixed Income | D24: =SUMIF(B2:B15,A24,D2:D15)
A25: Alternatives | D25: =SUMIF(B2:B15,A25,D2:D15)
A26: Cash | D26: =SUMIF(B2:B15,A26,D2:D15)

Sheet Covariance
A1: Portfolio Volatility (annualized) | B1: =SQRT(B2)
A2: Portfolio Variance | B2: =SUMPRODUCT(Assets!$D$2:$D$15,R6:R19)
B4: Weights (mirrored) -> | C4: =Assets!D2 | D4: =Assets!D3 | E4: =Assets!D4 | F4: =Assets!D5 | G4: =Assets!D6 | H4: =Assets!D7 | I4: =Assets!D8 | J4: =Assets!D9 | K4: =Assets!D10 | L4: =Assets!D11 | M4: =Assets!D12 | N4: =Assets!D13 | O4: =Assets!D14 | P4: =Assets!D15
B5: Cov Matrix -> | C5: US_Tech_Equity | D5: US_Healthcare_Equity | E5: US_Financials_Equity | F5: US_Energy_Equity | G5: US_Consumer_Equity | H5: European_Equity | I5: Emerging_Markets_Equity | J5: US_Govt_Bonds | K5: US_Corporate_Bonds | L5: Global_Bonds | M5: REIT | N5: Gold | O5: Commodities | P5: Money_Market | R5: Weighted Cov Row Sum
B6: US_Tech_Equity | C6: 0.065240053 | D6: 0.020956757 | E6: 0.038042862 | F6: 0.049315566 | G6: 0.023113086 | H6: 0.027557015 | I6: 0.031971853 | J6: -0.0013014489 | K6: 0.00087855335 | L6: -0.0021386855 | M6: 0.016754216 | N6: -0.0029967026 | O6: 0.02426646 | P6: -0.00011962003 | R6: =SUMPRODUCT($C$4:$P$4,C6:P6)
B7: US_Healthcare_Equity | C7: 0.020956757 | D7: 0.021541829 | E7: 0.018633102 | F7: 0.02612947 | G7: 0.013606825 | H7: 0.015360028 | I7: 0.017910046 | J7: 0.0001764777 | K7: 9.133106e-05 | L7: 0.00053022958 | M7: 0.012164025 | N7: 0.0021046596 | O7: 0.010599052 | P7: 2.8453199e-05 | R7: =SUMPRODUCT($C$4:$P$4,C7:P7)
B8: US_Financials_Equity | C8: 0.038042862 | D8: 0.018633102 | E8: 0.037807348 | F8: 0.038271183 | G8: 0.017483261 | H8: 0.02303202 | I8: 0.027645238 | J8: -0.0012125753 | K8: -5.9842097e-05 | L8: -0.0009530224 | M8: 0.014287843 | N8: 0.0016823138 | O8: 0.0099690056 | P8: 1.4789184e-05 | R8: =SUMPRODUCT($C$4:$P$4,C8:P8)
B9: US_Energy_Equity | C9: 0.049315566 | D9: 0.02612947 | E9: 0.038271183 | F9: 0.079857843 | G9: 0.025307893 | H9: 0.028480937 | I9: 0.03888216 | J9: 0.00011386522 | K9: -0.0013421761 | L9: -0.0011023921 | M9: 0.021760044 | N9: 0.0036788026 | O9: 0.022089922 | P9: -0.00013081836 | R9: =SUMPRODUCT($C$4:$P$4,C9:P9)
B10: US_Consumer_Equity | C10: 0.023113086 | D10: 0.013606825 | E10: 0.017483261 | F10: 0.025307893 | G10: 0.019331057 | H10: 0.015465682 | I10: 0.01783769 | J10: -0.0013272294 | K10: -0.0018689455 | L10: -0.00073328947 | M10: 0.0084921717 | N10: 0.0046727258 | O10: 0.0065823989 | P10: -9.1757915e-06 | R10: =SUMPRODUCT($C$4:$P$4,C10:P10)
B11: European_Equity | C11: 0.027557015 | D11: 0.015360028 | E11: 0.02303202 | F11: 0.028480937 | G11: 0.015465682 | H11: 0.03041344 | I11: 0.022224594 | J11: -0.0011863549 | K11: -0.0046445408 | L11: -0.0016585697 | M11: 0.0096571705 | N11: -0.00059335822 | O11: 0.014163185 | P11: -9.1258602e-05 | R11: =SUMPRODUCT($C$4:$P$4,C11:P11)
B12: Emerging_Markets_Equity | C12: 0.031971853 | D12: 0.017910046 | E12: 0.027645238 | F12: 0.03888216 | G12: 0.01783769 | H12: 0.022224594 | I12: 0.057019692 | J12: -0.004696365 | K12: -0.004146456 | L12: -0.0042296915 | M12: 0.011558086 | N12: 0.0072747216 | O12: 0.017728402 | P12: 5.1463571e-05 | R12: =SUMPRODUCT($C$4:$P$4,C12:P12)
B13: US_Govt_Bonds | C13: -0.0013014489 | D13: 0.0001764777 | E13: -0.0012125753 | F13: 0.00011386522 | G13: -0.0013272294 | H13: -0.0011863549 | I13: -0.004696365 | J13: 0.0028788804 | K13: 0.0023214595 | L13: 0.0024374125 | M13: 0.001714781 | N13: -0.0008012441 | O13: 0.0028750994 | P13: 1.2017249e-05 | R13: =SUMPRODUCT($C$4:$P$4,C13:P13)
B14: US_Corporate_Bonds | C14: 0.00087855335 | D14: 9.133106e-05 | E14: -5.9842097e-05 | F14: -0.0013421761 | G14: -0.0018689455 | H14: -0.0046445408 | I14: -0.004146456 | J14: 0.0023214595 | K14: 0.0066879841 | L14: 0.003900895 | M14: 0.0020714308 | N14: -0.0017963951 | O14: 0.00404143 | P14: 2.7016548e-05 | R14: =SUMPRODUCT($C$4:$P$4,C14:P14)
B15: Global_Bonds | C15: -0.0021386855 | D15: 0.00053022958 | E15: -0.0009530224 | F15: -0.0011023921 | G15: -0.00073328947 | H15: -0.0016585697 | I15: -0.0042296915 | J15: 0.0024374125 | K15: 0.003900895 | L15: 0.0056607718 | M15: 0.0033325225 | N15: -0.0013564875 | O15: 0.002971586 | P15: 2.0075807e-05 | R15: =SUMPRODUCT($C$4:$P$4,C15:P15)
B16: REIT | C16: 0.016754216 | D16: 0.012164025 | E16: 0.014287843 | F16: 0.021760044 | G16: 0.0084921717 | H16: 0.0096571705 | I16: 0.011558086 | J16: 0.001714781 | K16: 0.0020714308 | L16: 0.0033325225 | M16: 0.027009784 | N16: 0.00084835009 | O16: 0.0067586429 | P16: 6.0923618e-05 | R16: =SUMPRODUCT($C$4:$P$4,C16:P16)
B17: Gold | C17: -0.0029967026 | D17: 0.0021046596 | E17: 0.0016823138 | F17: 0.0036788026 | G17: 0.0046727258 | H17: -0.00059335822 | I17: 0.0072747216 | J17: -0.0008012441 | K17: -0.0017963951 | L17: -0.0013564875 | M17: 0.00084835009 | N17: 0.017554127 | O17: 0.0011523763 | P17: 0.00017216751 | R17: =SUMPRODUCT($C$4:$P$4,C17:P17)
... B19: Money_Market | C19: -0.00011962003 | D19: 2.8453199e-05 | E19: 1.4789184e-05 | F19: -0.00013081836 | G19: -9.1757915e-06 | H19: -9.1258602e-05 | I19: 5.1463571e-05 | J19: 1.2017249e-05 | K19: 2.7016548e-05 | L19: 2.0075807e-05 | M19: 6.0923618e-05 | N19: 0.00017216751 | O19: -0.00013689867 | P19: 2.7901307e-05 | R19: =SUMPRODUCT($C$4:$P$4,C19:P19)
